ornitho/__init__.py
ornitho/api_exception.py
ornitho/api_requester.py
ornitho/model/__init__.py
ornitho/model/abstract/__init__.py
ornitho/model/abstract/base_model.py
ornitho/model/abstract/createable_model.py
ornitho/model/abstract/deletable_model.py
ornitho/model/abstract/listable_model.py
ornitho/model/abstract/searchable_model.py
ornitho/model/abstract/updateable_model.py
ornitho/model/detail.py
ornitho/model/entity.py
ornitho/model/family.py
ornitho/model/field.py
ornitho/model/field_option.py
ornitho/model/form.py
ornitho/model/local_admin_unit.py
ornitho/model/media.py
ornitho/model/modification_type.py
ornitho/model/observation.py
ornitho/model/observer.py
ornitho/model/place.py
ornitho/model/protocol.py
ornitho/model/relation.py
ornitho/model/right.py
ornitho/model/site.py
ornitho/model/species.py
ornitho/model/taxo_group.py
ornitho/model/territorial_unit.py
ornitho-0.3.0.dist-info/LICENSE
ornitho-0.3.0.dist-info/WHEEL
ornitho-0.3.0.dist-info/METADATA
ornitho-0.3.0.dist-info/RECORD
