Metadata-Version: 2.1
Name: ornitho
Version: 0.3.0
Summary: An ornitho API client
Home-page: https://github.com/dda-dev/ornitho-client-python
License: MIT
Author: Patrick Lindel
Author-email: lindel@dda-web.de
Requires-Python: >=3.7,<4.0
Classifier: Development Status :: 4 - Beta
Classifier: License :: OSI Approved :: MIT License
Classifier: Programming Language :: Python :: 3
Classifier: Programming Language :: Python :: 3 :: Only
Classifier: Programming Language :: Python :: 3.10
Classifier: Programming Language :: Python :: 3.7
Classifier: Programming Language :: Python :: 3.8
Classifier: Programming Language :: Python :: 3.9
Provides-Extra: caching
Requires-Dist: pytz
Requires-Dist: requests-cache (>=0.9.3,<0.10.0); extra == "caching"
Requires-Dist: requests-oauthlib
Project-URL: Repository, https://github.com/dda-dev/ornitho-client-python
